bdantic/__init__.py
bdantic/models/__init__.py
bdantic/models/base.py
bdantic/models/base_test.py
bdantic/models/data.py
bdantic/models/data_test.py
bdantic/models/directives.py
bdantic/models/directives_test.py
bdantic/models/display.py
bdantic/models/display_test.py
bdantic/models/file.py
bdantic/models/file_test.py
bdantic/models/query.py
bdantic/models/query_test.py
bdantic/models/realize.py
bdantic/models/realize_test.py
bdantic/parse.py
bdantic/parse_test.py
bdantic/py.typed
bdantic/types.py
bdantic-0.2.6.dist-info/LICENSE
bdantic-0.2.6.dist-info/WHEEL
bdantic-0.2.6.dist-info/METADATA
bdantic-0.2.6.dist-info/RECORD
