Metadata-Version: 2.1
Name: bdantic
Version: 0.2.6
Summary: A package for extending beancount with pydantic
Home-page: https://github.com/jmgilman/bdantic
License: MIT
Keywords: beancount,pydantic,models
Author: Joshua Gilman
Author-email: joshuagilman@gmail.com
Requires-Python: >=3.8,<4.0
Classifier: License :: OSI Approved :: MIT License
Classifier: Programming Language :: Python :: 3
Classifier: Programming Language :: Python :: 3.10
Classifier: Programming Language :: Python :: 3.8
Classifier: Programming Language :: Python :: 3.9
Requires-Dist: beancount (>=2.3.4,<3.0.0)
Requires-Dist: beancount-stubs (>=0.1.3,<0.2.0)
Requires-Dist: jmespath (>=0.10.0,<0.11.0)
Requires-Dist: orjson (>=3.6.6,<4.0.0)
Requires-Dist: pydantic (>=1.9.0,<2.0.0)
Project-URL: Repository, https://github.com/jmgilman/bdantic
